{
  "resourceType": "OperationOutcome",
  "meta": {
    "profile": [
      "https://fhir.nhs.uk/STU3/StructureDefinition/GPConnect-OperationOutcome-1"
    ]
  },
  "issue": [
    {
      "severity": "error",
      "code": "not-supported",
      "details": {
        "coding": [
          {
            "system": "https://fhir.nhs.uk/STU3/ValueSet/Spine-ErrorOrWarningCode-1",
            "code": "METHOD_NOT_SUPPORTED",
            "display": "Method not supported"
          }
        ]
      },
      "diagnostics": "Request method '{{requestMethod}}' not supported"
    }
  ]
}